{
 "cells": [
  {
   "cell_type": "code",
   "execution_count": 32,
   "metadata": {},
   "outputs": [],
   "source": [
    "import random\n",
    "import dis\n",
    "from random import randint"
   ]
  },
  {
   "cell_type": "code",
   "execution_count": 33,
   "metadata": {},
   "outputs": [],
   "source": [
    "def f1():\n",
    "    return randint(1, 11)"
   ]
  },
  {
   "cell_type": "code",
   "execution_count": 34,
   "metadata": {},
   "outputs": [],
   "source": [
    "def f2():\n",
    "    return random.randint(1, 11)"
   ]
  },
  {
   "cell_type": "code",
   "execution_count": 35,
   "metadata": {},
   "outputs": [
    {
     "name": "stdout",
     "output_type": "stream",
     "text": [
      "  2           0 LOAD_GLOBAL              0 (randint)\n",
      "              2 LOAD_CONST               1 (1)\n",
      "              4 LOAD_CONST               2 (11)\n",
      "              6 CALL_FUNCTION            2\n",
      "              8 RETURN_VALUE\n"
     ]
    }
   ],
   "source": [
    "dis.dis(f1)"
   ]
  },
  {
   "cell_type": "code",
   "execution_count": 36,
   "metadata": {},
   "outputs": [
    {
     "name": "stdout",
     "output_type": "stream",
     "text": [
      "  2           0 LOAD_GLOBAL              0 (random)\n",
      "              2 LOAD_METHOD              1 (randint)\n",
      "              4 LOAD_CONST               1 (1)\n",
      "              6 LOAD_CONST               2 (11)\n",
      "              8 CALL_METHOD              2\n",
      "             10 RETURN_VALUE\n"
     ]
    }
   ],
   "source": [
    "dis.dis(f2)"
   ]
  },
  {
   "cell_type": "code",
   "execution_count": 37,
   "metadata": {},
   "outputs": [
    {
     "name": "stdout",
     "output_type": "stream",
     "text": [
      "1.26 µs ± 36.6 ns per loop (mean ± std. dev. of 7 runs, 1000000 loops each)\n"
     ]
    }
   ],
   "source": [
    "%timeit f1()"
   ]
  },
  {
   "cell_type": "code",
   "execution_count": 31,
   "metadata": {},
   "outputs": [
    {
     "name": "stdout",
     "output_type": "stream",
     "text": [
      "1.43 µs ± 37.8 ns per loop (mean ± std. dev. of 7 runs, 1000000 loops each)\n"
     ]
    }
   ],
   "source": [
    "%timeit f2()"
   ]
  },
  {
   "cell_type": "code",
   "execution_count": null,
   "metadata": {},
   "outputs": [],
   "source": []
  },
  {
   "cell_type": "code",
   "execution_count": null,
   "metadata": {},
   "outputs": [],
   "source": []
  }
 ],
 "metadata": {
  "kernelspec": {
   "display_name": "Python 3",
   "language": "python",
   "name": "python3"
  },
  "language_info": {
   "codemirror_mode": {
    "name": "ipython",
    "version": 3
   },
   "file_extension": ".py",
   "mimetype": "text/x-python",
   "name": "python",
   "nbconvert_exporter": "python",
   "pygments_lexer": "ipython3",
   "version": "3.7.3"
  }
 },
 "nbformat": 4,
 "nbformat_minor": 2
}
